configini/__init__.py
configini/casting.py
configini/data_types.py
configini-1.1.dist-info/LICENSE.txt
configini-1.1.dist-info/METADATA
configini-1.1.dist-info/WHEEL
configini-1.1.dist-info/top_level.txt
configini-1.1.dist-info/RECORD
