Metadata-Version: 2.1
Name: configini
Version: 1.1
Summary: Small package to easily parse an .ini file.
Home-page: https://github.com/Spider-Frog/configini
Author: SpiderFrog
Author-email: germanspiderfrog@gmail.com
License: UNKNOWN
Platform: UNKNOWN
Classifier: Programming Language :: Python :: 3
Classifier: Operating System :: OS Independent
Requires-Python: >=3.6
License-File: LICENSE.txt
